vteklib/__init__.py
vteklib/drawer.py
vteklib/plot_data.py
vteklib/regressions/__init__.py
vteklib/regressions/linear.py
vteklib/regressions/poly.py
vteklib/regressions/regression.py
vteklib/utils/__init__.py
vteklib/utils/excel_parser.py
vteklib-0.1.2.dist-info/LICENSE.md
vteklib-0.1.2.dist-info/METADATA
vteklib-0.1.2.dist-info/WHEEL
vteklib-0.1.2.dist-info/top_level.txt
vteklib-0.1.2.dist-info/RECORD
