Metadata-Version: 2.1
Name: vteklib
Version: 0.1.2
Summary: Wrapper around matplotlib for easier 2D approximation & scientific-style plots
Home-page: https://github.com/mixx3/vteklib
Author: Mike Parfenov
Author-email: mmikee00800@gmail.com
License: BSD 2-Clause "Simplified"
License-File: LICENSE.md
Requires-Dist: numpy
Requires-Dist: matplotlib
Requires-Dist: pandas
Requires-Dist: sklearn
Requires-Dist: scipy
Requires-Dist: openpyxl
